{
  "schemaVersion": 1,
  "kind": "switch-family",
  "slug": "bsun-raw",
  "title": "Bsun Raw",
  "category": "switches",
  "familyKind": "unclassified",
  "recipeStatus": "not_assessed",
  "variants": [
    {
      "label": "기본 구성",
      "reference": true,
      "rating": 2,
      "manufacturer": "Bsun",
      "footprintType": "Cherry MX",
      "switchTypes": [
        "Linear"
      ],
      "spring": {
        "resolution": "stock_unresolved",
        "name": "Factory OG 60g",
        "status": "partial"
      },
      "housingFit": {
        "state": "none",
        "method": null,
        "material": null
      }
    }
  ],
  "parts": [],
  "images": [
    {
      "alt": "Bsun Raw 사진 1",
      "variants": [
        {
          "src": "/media/switches/bsun-raw/674f6bf221a16827-source-gallery-0-6232e0f870d6-640.avif",
          "width": 640,
          "height": 557
        },
        {
          "src": "/media/switches/bsun-raw/674f6bf221a16827-source-gallery-0-6232e0f870d6-1280.avif",
          "width": 974,
          "height": 848
        }
      ]
    },
    {
      "alt": "Bsun Raw 사진 2",
      "variants": [
        {
          "src": "/media/switches/bsun-raw/674f6bf221a16827-source-gallery-1-ca1e48dc20e5-640.avif",
          "width": 640,
          "height": 574
        },
        {
          "src": "/media/switches/bsun-raw/674f6bf221a16827-source-gallery-1-ca1e48dc20e5-1280.avif",
          "width": 1280,
          "height": 1147
        },
        {
          "src": "/media/switches/bsun-raw/674f6bf221a16827-source-gallery-1-ca1e48dc20e5-2400.avif",
          "width": 1350,
          "height": 1210
        }
      ]
    }
  ]
}
