{
  "schemaVersion": 1,
  "kind": "keyboard",
  "slug": "transition-lite-no-7",
  "title": "Transition Lite No.7",
  "category": "keyboards",
  "status": "빌드 완료",
  "lastBuiltAt": "2025-10-18",
  "modules": [],
  "plates": [
    "ABS",
    "PC",
    "믹스보강"
  ],
  "ergonomicFeatures": [],
  "layouts": [
    "모노블럭",
    "로우스태거",
    "80%"
  ],
  "mounts": [
    "탑 마운트"
  ],
  "foams": [
    "노폼"
  ],
  "images": [
    {
      "alt": "Transition Lite No.7 사진 1",
      "variants": [
        {
          "src": "/media/keyboards/transition-lite-no-7/07e2360dac435fcc-0-640.avif",
          "width": 640,
          "height": 408
        },
        {
          "src": "/media/keyboards/transition-lite-no-7/07e2360dac435fcc-0-1280.avif",
          "width": 1280,
          "height": 816
        },
        {
          "src": "/media/keyboards/transition-lite-no-7/07e2360dac435fcc-0-2400.avif",
          "width": 2400,
          "height": 1530
        }
      ]
    }
  ]
}
